<?xml version="1.0" encoding="iso-8859-1" standalone="no"?>
<comments
  xmlns:xsi='http://www.w3.org/2001/XMLSchema-instance'
  xsi:noNamespaceSchemaLocation='comments.xsd'
  name="Spigot_to_Paper"
  jdversion="1.1.0">

<!-- This file contains comments for a JDiff report. -->
<!-- It is used only in generating the report, and does not need to ship with the final report. -->

<!-- The id attribute in an identifier element identifies the change as noted in the report. -->
<!-- An id has the form package[.class[.[ctor|method|field].signature]], where [] indicates optional text. -->
<!-- A comment element can have multiple identifier elements, which will -->
<!-- will cause the same text to appear at each place in the report, but -->
<!-- will be converted to separate comments when the comments file is used. -->
<!-- HTML tags in the text field will appear in the report. -->
<!-- You also need to close p HTML elements, used for paragraphs - see the top-level documentation. -->
<comment>
  <identifier id="com.destroystokyo"/>
  <text>
    InsertCommentsHere
  </text>
</comment>
<comment>
  <identifier id="io.papermc"/>
  <text>
    InsertCommentsHere
  </text>
</comment>
<comment>
  <identifier id="org.bukkit"/>
  <text>
    InsertCommentsHere
  </text>
</comment>
<comment>
  <identifier id="org.bukkit.Bukkit"/>
  <text>
    InsertCommentsHere
  </text>
</comment>
<comment>
  <identifier id="org.bukkit.Bukkit.broadcastMessage_changed(java.lang.String)"/>
  <text>
    InsertCommentsHere
  </text>
</comment>
<comment>
  <identifier id="org.bukkit.Bukkit.broadcast_added(net.kyori.adventure.text.Component, java.lang.String)"/>
  <text>
    InsertCommentsHere
  </text>
</comment>
<comment>
  <identifier id="org.bukkit.Bukkit.broadcast_added(net.md_5.bungee.api.chat.BaseComponent)"/>
  <text>
    InsertCommentsHere
  </text>
</comment>
<comment>
  <identifier id="org.bukkit.Bukkit.broadcast_added(net.md_5.bungee.api.chat.BaseComponent[])"/>
  <text>
    InsertCommentsHere
  </text>
</comment>
<comment>
  <identifier id="org.bukkit.Bukkit.broadcast_removed(java.lang.String, java.lang.String)"/>
  <text>
    InsertCommentsHere
  </text>
</comment>
<comment>
  <identifier id="org.bukkit.Bukkit.createInventory_added(org.bukkit.inventory.InventoryHolder, int, net.kyori.adventure.text.Component)"/>
  <text>
    InsertCommentsHere
  </text>
</comment>
<comment>
  <identifier id="org.bukkit.Bukkit.createInventory_added(org.bukkit.inventory.InventoryHolder, org.bukkit.event.inventory.InventoryType, net.kyori.adventure.text.Component)"/>
  <text>
    InsertCommentsHere
  </text>
</comment>
<comment>
  <identifier id="org.bukkit.Bukkit.createInventory_removed(org.bukkit.inventory.InventoryHolder, int, java.lang.String)"/>
  <text>
    InsertCommentsHere
  </text>
</comment>
<comment>
  <identifier id="org.bukkit.Bukkit.createInventory_removed(org.bukkit.inventory.InventoryHolder, org.bukkit.event.inventory.InventoryType, java.lang.String)"/>
  <text>
    InsertCommentsHere
  </text>
</comment>
<comment>
  <identifier id="org.bukkit.Bukkit.createMerchant_changed(net.kyori.adventure.text.Component)"/>
  <text>
    InsertCommentsHere
  </text>
</comment>
<comment>
  <identifier id="org.bukkit.Bukkit.createProfile_added(java.lang.String)"/>
  <text>
    InsertCommentsHere
  </text>
</comment>
<comment>
  <identifier id="org.bukkit.Bukkit.createProfile_added(java.util.UUID)"/>
  <text>
    InsertCommentsHere
  </text>
</comment>
<comment>
  <identifier id="org.bukkit.Bukkit.createProfile_added(java.util.UUID, java.lang.String)"/>
  <text>
    InsertCommentsHere
  </text>
</comment>
<comment>
  <identifier id="org.bukkit.Bukkit.createVanillaChunkData_added(org.bukkit.World, int, int)"/>
  <text>
    InsertCommentsHere
  </text>
</comment>
<comment>
  <identifier id="org.bukkit.Bukkit.getAverageTickTime_added()"/>
  <text>
    InsertCommentsHere
  </text>
</comment>
<comment>
  <identifier id="org.bukkit.Bukkit.getCommandMap_added()"/>
  <text>
    InsertCommentsHere
  </text>
</comment>
<comment>
  <identifier id="org.bukkit.Bukkit.getCurrentTick_added()"/>
  <text>
    InsertCommentsHere
  </text>
</comment>
<comment>
  <identifier id="org.bukkit.Bukkit.getMinecraftVersion_added()"/>
  <text>
    InsertCommentsHere
  </text>
</comment>
<comment>
  <identifier id="org.bukkit.Bukkit.getMobGoals_added()"/>
  <text>
    InsertCommentsHere
  </text>
</comment>
<comment>
  <identifier id="org.bukkit.Bukkit.getMotd_changed()"/>
  <text>
    InsertCommentsHere
  </text>
</comment>
<comment>
  <identifier id="org.bukkit.Bukkit.getOfflinePlayerIfCached_added(java.lang.String)"/>
  <text>
    InsertCommentsHere
  </text>
</comment>
<comment>
  <identifier id="org.bukkit.Bukkit.getPermissionMessage_added()"/>
  <text>
    InsertCommentsHere
  </text>
</comment>
<comment>
  <identifier id="org.bukkit.Bukkit.getPlayerUniqueId_added(java.lang.String)"/>
  <text>
    InsertCommentsHere
  </text>
</comment>
<comment>
  <identifier id="org.bukkit.Bukkit.getShutdownMessage_changed()"/>
  <text>
    InsertCommentsHere
  </text>
</comment>
<comment>
  <identifier id="org.bukkit.Bukkit.getTPS_added()"/>
  <text>
    InsertCommentsHere
  </text>
</comment>
<comment>
  <identifier id="org.bukkit.Bukkit.getTickTimes_added()"/>
  <text>
    InsertCommentsHere
  </text>
</comment>
<comment>
  <identifier id="org.bukkit.Bukkit.getWorld_added(org.bukkit.NamespacedKey)"/>
  <text>
    InsertCommentsHere
  </text>
</comment>
<comment>
  <identifier id="org.bukkit.Bukkit.isStopping_added()"/>
  <text>
    InsertCommentsHere
  </text>
</comment>
<comment>
  <identifier id="org.bukkit.Bukkit.motd_added()"/>
  <text>
    InsertCommentsHere
  </text>
</comment>
<comment>
  <identifier id="org.bukkit.Bukkit.reloadCommandAliases_added()"/>
  <text>
    InsertCommentsHere
  </text>
</comment>
<comment>
  <identifier id="org.bukkit.Bukkit.reloadPermissions_added()"/>
  <text>
    InsertCommentsHere
  </text>
</comment>
<comment>
  <identifier id="org.bukkit.Bukkit.setMaxPlayers_added(int)"/>
  <text>
    InsertCommentsHere
  </text>
</comment>
<comment>
  <identifier id="org.bukkit.Bukkit.shutdownMessage_added()"/>
  <text>
    InsertCommentsHere
  </text>
</comment>
<comment>
  <identifier id="org.bukkit.Bukkit.suggestPlayerNamesWhenNullTabCompletions_added()"/>
  <text>
    InsertCommentsHere
  </text>
</comment>
<comment>
  <identifier id="org.bukkit.Chunk"/>
  <text>
    InsertCommentsHere
  </text>
</comment>
<comment>
  <identifier id="org.bukkit.Chunk.getChunkKey_added()"/>
  <text>
    InsertCommentsHere
  </text>
</comment>
<comment>
  <identifier id="org.bukkit.Chunk.getChunkKey_added(int, int)"/>
  <text>
    InsertCommentsHere
  </text>
</comment>
<comment>
  <identifier id="org.bukkit.Chunk.getChunkKey_added(org.bukkit.Location)"/>
  <text>
    InsertCommentsHere
  </text>
</comment>
<comment>
  <identifier id="org.bukkit.Chunk.getTileEntities_added()"/>
  <text>
    InsertCommentsHere
  </text>
</comment>
<comment>
  <identifier id="org.bukkit.Chunk.getTileEntities_added(boolean)"/>
  <text>
    InsertCommentsHere
  </text>
</comment>
<comment>
  <identifier id="org.bukkit.Chunk.getTileEntities_added(java.util.function.Predicate&lt;org.bukkit.block.Block&gt;, boolean)"/>
  <text>
    InsertCommentsHere
  </text>
</comment>
<comment>
  <identifier id="org.bukkit.Chunk.getTileEntities_removed()"/>
  <text>
    InsertCommentsHere
  </text>
</comment>
<comment>
  <identifier id="org.bukkit.Location"/>
  <text>
    InsertCommentsHere
  </text>
</comment>
<comment>
  <identifier id="org.bukkit.Location.add_added(org.bukkit.Location, double, double, double)"/>
  <text>
    InsertCommentsHere
  </text>
</comment>
<comment>
  <identifier id="org.bukkit.Location.createExplosion_added(float)"/>
  <text>
    InsertCommentsHere
  </text>
</comment>
<comment>
  <identifier id="org.bukkit.Location.createExplosion_added(float, boolean)"/>
  <text>
    InsertCommentsHere
  </text>
</comment>
<comment>
  <identifier id="org.bukkit.Location.createExplosion_added(float, boolean, boolean)"/>
  <text>
    InsertCommentsHere
  </text>
</comment>
<comment>
  <identifier id="org.bukkit.Location.createExplosion_added(org.bukkit.entity.Entity, float)"/>
  <text>
    InsertCommentsHere
  </text>
</comment>
<comment>
  <identifier id="org.bukkit.Location.createExplosion_added(org.bukkit.entity.Entity, float, boolean)"/>
  <text>
    InsertCommentsHere
  </text>
</comment>
<comment>
  <identifier id="org.bukkit.Location.createExplosion_added(org.bukkit.entity.Entity, float, boolean, boolean)"/>
  <text>
    InsertCommentsHere
  </text>
</comment>
<comment>
  <identifier id="org.bukkit.Location.getNearbyEntitiesByType_added(java.lang.Class&lt;? extends T&gt;, double)"/>
  <text>
    InsertCommentsHere
  </text>
</comment>
<comment>
  <identifier id="org.bukkit.Location.getNearbyEntitiesByType_added(java.lang.Class&lt;? extends T&gt;, double, double)"/>
  <text>
    InsertCommentsHere
  </text>
</comment>
<comment>
  <identifier id="org.bukkit.Location.getNearbyEntitiesByType_added(java.lang.Class&lt;? extends T&gt;, double, double, double)"/>
  <text>
    InsertCommentsHere
  </text>
</comment>
<comment>
  <identifier id="org.bukkit.Location.getNearbyEntitiesByType_added(java.lang.Class&lt;? extends T&gt;, double, double, java.util.function.Predicate&lt;T&gt;)"/>
  <text>
    InsertCommentsHere
  </text>
</comment>
<comment>
  <identifier id="org.bukkit.Location.getNearbyEntitiesByType_added(java.lang.Class&lt;? extends T&gt;, double, java.util.function.Predicate&lt;T&gt;)"/>
  <text>
    InsertCommentsHere
  </text>
</comment>
<comment>
  <identifier id="org.bukkit.Location.getNearbyEntitiesByType_added(java.lang.Class&lt;? extends org.bukkit.entity.Entity&gt;, double, double, double, java.util.function.Predicate&lt;T&gt;)"/>
  <text>
    InsertCommentsHere
  </text>
</comment>
<comment>
  <identifier id="org.bukkit.Location.getNearbyEntities_added(double, double, double)"/>
  <text>
    InsertCommentsHere
  </text>
</comment>
<comment>
  <identifier id="org.bukkit.Location.getNearbyLivingEntities_added(double)"/>
  <text>
    InsertCommentsHere
  </text>
</comment>
<comment>
  <identifier id="org.bukkit.Location.getNearbyLivingEntities_added(double, double)"/>
  <text>
    InsertCommentsHere
  </text>
</comment>
<comment>
  <identifier id="org.bukkit.Location.getNearbyLivingEntities_added(double, double, double)"/>
  <text>
    InsertCommentsHere
  </text>
</comment>
<comment>
  <identifier id="org.bukkit.Location.getNearbyLivingEntities_added(double, double, double, java.util.function.Predicate&lt;org.bukkit.entity.LivingEntity&gt;)"/>
  <text>
    InsertCommentsHere
  </text>
</comment>
<comment>
  <identifier id="org.bukkit.Location.getNearbyLivingEntities_added(double, double, java.util.function.Predicate&lt;org.bukkit.entity.LivingEntity&gt;)"/>
  <text>
    InsertCommentsHere
  </text>
</comment>
<comment>
  <identifier id="org.bukkit.Location.getNearbyLivingEntities_added(double, java.util.function.Predicate&lt;org.bukkit.entity.LivingEntity&gt;)"/>
  <text>
    InsertCommentsHere
  </text>
</comment>
<comment>
  <identifier id="org.bukkit.Location.getNearbyPlayers_added(double)"/>
  <text>
    InsertCommentsHere
  </text>
</comment>
<comment>
  <identifier id="org.bukkit.Location.getNearbyPlayers_added(double, double)"/>
  <text>
    InsertCommentsHere
  </text>
</comment>
<comment>
  <identifier id="org.bukkit.Location.getNearbyPlayers_added(double, double, double)"/>
  <text>
    InsertCommentsHere
  </text>
</comment>
<comment>
  <identifier id="org.bukkit.Location.getNearbyPlayers_added(double, double, double, java.util.function.Predicate&lt;org.bukkit.entity.Player&gt;)"/>
  <text>
    InsertCommentsHere
  </text>
</comment>
<comment>
  <identifier id="org.bukkit.Location.getNearbyPlayers_added(double, double, java.util.function.Predicate&lt;org.bukkit.entity.Player&gt;)"/>
  <text>
    InsertCommentsHere
  </text>
</comment>
<comment>
  <identifier id="org.bukkit.Location.getNearbyPlayers_added(double, java.util.function.Predicate&lt;org.bukkit.entity.Player&gt;)"/>
  <text>
    InsertCommentsHere
  </text>
</comment>
<comment>
  <identifier id="org.bukkit.Location.isChunkLoaded_added()"/>
  <text>
    InsertCommentsHere
  </text>
</comment>
<comment>
  <identifier id="org.bukkit.Location.isGenerated_added()"/>
  <text>
    InsertCommentsHere
  </text>
</comment>
<comment>
  <identifier id="org.bukkit.Location.set_added(double, double, double)"/>
  <text>
    InsertCommentsHere
  </text>
</comment>
<comment>
  <identifier id="org.bukkit.Location.subtract_added(org.bukkit.Location, double, double, double)"/>
  <text>
    InsertCommentsHere
  </text>
</comment>
<comment>
  <identifier id="org.bukkit.Location.toBlockKey_added()"/>
  <text>
    InsertCommentsHere
  </text>
</comment>
<comment>
  <identifier id="org.bukkit.Location.toBlockLocation_added()"/>
  <text>
    InsertCommentsHere
  </text>
</comment>
<comment>
  <identifier id="org.bukkit.Location.toCenterLocation_added()"/>
  <text>
    InsertCommentsHere
  </text>
</comment>
<comment>
  <identifier id="org.bukkit.Location.toHighestLocation_added()"/>
  <text>
    InsertCommentsHere
  </text>
</comment>
<comment>
  <identifier id="org.bukkit.Location.toHighestLocation_added(com.destroystokyo.paper.HeightmapType)"/>
  <text>
    InsertCommentsHere
  </text>
</comment>
<comment>
  <identifier id="org.bukkit.Location.toHighestLocation_added(org.bukkit.HeightMap)"/>
  <text>
    InsertCommentsHere
  </text>
</comment>
<comment>
  <identifier id="org.bukkit.Material"/>
  <text>
    InsertCommentsHere
  </text>
</comment>
<comment>
  <identifier id="org.bukkit.Material.getTranslationKey_added()"/>
  <text>
    InsertCommentsHere
  </text>
</comment>
<comment>
  <identifier id="org.bukkit.Material.isEmpty_added()"/>
  <text>
    InsertCommentsHere
  </text>
</comment>
<comment>
  <identifier id="org.bukkit.Nameable"/>
  <text>
    InsertCommentsHere
  </text>
</comment>
<comment>
  <identifier id="org.bukkit.Nameable.customName_added()"/>
  <text>
    InsertCommentsHere
  </text>
</comment>
<comment>
  <identifier id="org.bukkit.Nameable.customName_added(net.kyori.adventure.text.Component)"/>
  <text>
    InsertCommentsHere
  </text>
</comment>
<comment>
  <identifier id="org.bukkit.NamespacedKey"/>
  <text>
    InsertCommentsHere
  </text>
</comment>
<comment>
  <identifier id="org.bukkit.NamespacedKey.asString_added()"/>
  <text>
    InsertCommentsHere
  </text>
</comment>
<comment>
  <identifier id="org.bukkit.NamespacedKey.namespace_added()"/>
  <text>
    InsertCommentsHere
  </text>
</comment>
<comment>
  <identifier id="org.bukkit.NamespacedKey.value_added()"/>
  <text>
    InsertCommentsHere
  </text>
</comment>
<comment>
  <identifier id="org.bukkit.OfflinePlayer"/>
  <text>
    InsertCommentsHere
  </text>
</comment>
<comment>
  <identifier id="org.bukkit.OfflinePlayer.banPlayer_added(java.lang.String)"/>
  <text>
    InsertCommentsHere
  </text>
</comment>
<comment>
  <identifier id="org.bukkit.OfflinePlayer.banPlayer_added(java.lang.String, java.lang.String)"/>
  <text>
    InsertCommentsHere
  </text>
</comment>
<comment>
  <identifier id="org.bukkit.OfflinePlayer.banPlayer_added(java.lang.String, java.util.Date)"/>
  <text>
    InsertCommentsHere
  </text>
</comment>
<comment>
  <identifier id="org.bukkit.OfflinePlayer.banPlayer_added(java.lang.String, java.util.Date, java.lang.String)"/>
  <text>
    InsertCommentsHere
  </text>
</comment>
<comment>
  <identifier id="org.bukkit.OfflinePlayer.banPlayer_added(java.lang.String, java.util.Date, java.lang.String, boolean)"/>
  <text>
    InsertCommentsHere
  </text>
</comment>
<comment>
  <identifier id="org.bukkit.OfflinePlayer.getLastLogin_added()"/>
  <text>
    InsertCommentsHere
  </text>
</comment>
<comment>
  <identifier id="org.bukkit.OfflinePlayer.getLastPlayed_changed()"/>
  <text>
    InsertCommentsHere
  </text>
</comment>
<comment>
  <identifier id="org.bukkit.OfflinePlayer.getLastSeen_added()"/>
  <text>
    InsertCommentsHere
  </text>
</comment>
<comment>
  <identifier id="org.bukkit.Particle"/>
  <text>
    InsertCommentsHere
  </text>
</comment>
<comment>
  <identifier id="org.bukkit.Particle.builder_added()"/>
  <text>
    InsertCommentsHere
  </text>
</comment>
<comment>
  <identifier id="org.bukkit.Server"/>
  <text>
    InsertCommentsHere
  </text>
</comment>
<comment>
  <identifier id="org.bukkit.Server.Spigot"/>
  <text>
    InsertCommentsHere
  </text>
</comment>
<comment>
  <identifier id="org.bukkit.Server.Spigot.broadcast_changed(net.md_5.bungee.api.chat.BaseComponent)"/>
  <text>
    InsertCommentsHere
  </text>
</comment>
<comment>
  <identifier id="org.bukkit.Server.Spigot.broadcast_changed(net.md_5.bungee.api.chat.BaseComponent[])"/>
  <text>
    InsertCommentsHere
  </text>
</comment>
<comment>
  <identifier id="org.bukkit.Server.Spigot.getBukkitConfig_added()"/>
  <text>
    InsertCommentsHere
  </text>
</comment>
<comment>
  <identifier id="org.bukkit.Server.Spigot.getPaperConfig_added()"/>
  <text>
    InsertCommentsHere
  </text>
</comment>
<comment>
  <identifier id="org.bukkit.Server.Spigot.getSpigotConfig_added()"/>
  <text>
    InsertCommentsHere
  </text>
</comment>
<comment>
  <identifier id="org.bukkit.Server.broadcastMessage_changed(java.lang.String)"/>
  <text>
    InsertCommentsHere
  </text>
</comment>
<comment>
  <identifier id="org.bukkit.Server.broadcast_added(java.lang.String, java.lang.String)"/>
  <text>
    InsertCommentsHere
  </text>
</comment>
<comment>
  <identifier id="org.bukkit.Server.broadcast_added(net.kyori.adventure.text.Component, java.lang.String)"/>
  <text>
    InsertCommentsHere
  </text>
</comment>
<comment>
  <identifier id="org.bukkit.Server.broadcast_added(net.md_5.bungee.api.chat.BaseComponent)"/>
  <text>
    InsertCommentsHere
  </text>
</comment>
<comment>
  <identifier id="org.bukkit.Server.broadcast_added(net.md_5.bungee.api.chat.BaseComponent[])"/>
  <text>
    InsertCommentsHere
  </text>
</comment>
<comment>
  <identifier id="org.bukkit.Server.broadcast_removed(java.lang.String, java.lang.String)"/>
  <text>
    InsertCommentsHere
  </text>
</comment>
<comment>
  <identifier id="org.bukkit.Server.createInventory_added(org.bukkit.inventory.InventoryHolder, int, net.kyori.adventure.text.Component)"/>
  <text>
    InsertCommentsHere
  </text>
</comment>
<comment>
  <identifier id="org.bukkit.Server.createInventory_added(org.bukkit.inventory.InventoryHolder, org.bukkit.event.inventory.InventoryType, net.kyori.adventure.text.Component)"/>
  <text>
    InsertCommentsHere
  </text>
</comment>
<comment>
  <identifier id="org.bukkit.Server.createInventory_removed(org.bukkit.inventory.InventoryHolder, int, java.lang.String)"/>
  <text>
    InsertCommentsHere
  </text>
</comment>
<comment>
  <identifier id="org.bukkit.Server.createInventory_removed(org.bukkit.inventory.InventoryHolder, org.bukkit.event.inventory.InventoryType, java.lang.String)"/>
  <text>
    InsertCommentsHere
  </text>
</comment>
<comment>
  <identifier id="org.bukkit.Server.createMerchant_changed(net.kyori.adventure.text.Component)"/>
  <text>
    InsertCommentsHere
  </text>
</comment>
<comment>
  <identifier id="org.bukkit.Server.createProfile_added(java.lang.String)"/>
  <text>
    InsertCommentsHere
  </text>
</comment>
<comment>
  <identifier id="org.bukkit.Server.createProfile_added(java.util.UUID)"/>
  <text>
    InsertCommentsHere
  </text>
</comment>
<comment>
  <identifier id="org.bukkit.Server.createProfile_added(java.util.UUID, java.lang.String)"/>
  <text>
    InsertCommentsHere
  </text>
</comment>
<comment>
  <identifier id="org.bukkit.Server.createVanillaChunkData_added(org.bukkit.World, int, int)"/>
  <text>
    InsertCommentsHere
  </text>
</comment>
<comment>
  <identifier id="org.bukkit.Server.getAverageTickTime_added()"/>
  <text>
    InsertCommentsHere
  </text>
</comment>
<comment>
  <identifier id="org.bukkit.Server.getCommandMap_added()"/>
  <text>
    InsertCommentsHere
  </text>
</comment>
<comment>
  <identifier id="org.bukkit.Server.getCurrentTick_added()"/>
  <text>
    InsertCommentsHere
  </text>
</comment>
<comment>
  <identifier id="org.bukkit.Server.getMinecraftVersion_added()"/>
  <text>
    InsertCommentsHere
  </text>
</comment>
<comment>
  <identifier id="org.bukkit.Server.getMobGoals_added()"/>
  <text>
    InsertCommentsHere
  </text>
</comment>
<comment>
  <identifier id="org.bukkit.Server.getMotd_changed()"/>
  <text>
    InsertCommentsHere
  </text>
</comment>
<comment>
  <identifier id="org.bukkit.Server.getOfflinePlayerIfCached_added(java.lang.String)"/>
  <text>
    InsertCommentsHere
  </text>
</comment>
<comment>
  <identifier id="org.bukkit.Server.getPermissionMessage_added()"/>
  <text>
    InsertCommentsHere
  </text>
</comment>
<comment>
  <identifier id="org.bukkit.Server.getPlayerUniqueId_added(java.lang.String)"/>
  <text>
    InsertCommentsHere
  </text>
</comment>
<comment>
  <identifier id="org.bukkit.Server.getShutdownMessage_changed()"/>
  <text>
    InsertCommentsHere
  </text>
</comment>
<comment>
  <identifier id="org.bukkit.Server.getTPS_added()"/>
  <text>
    InsertCommentsHere
  </text>
</comment>
<comment>
  <identifier id="org.bukkit.Server.getTickTimes_added()"/>
  <text>
    InsertCommentsHere
  </text>
</comment>
<comment>
  <identifier id="org.bukkit.Server.getWorld_added(org.bukkit.NamespacedKey)"/>
  <text>
    InsertCommentsHere
  </text>
</comment>
<comment>
  <identifier id="org.bukkit.Server.isStopping_added()"/>
  <text>
    InsertCommentsHere
  </text>
</comment>
<comment>
  <identifier id="org.bukkit.Server.motd_added()"/>
  <text>
    InsertCommentsHere
  </text>
</comment>
<comment>
  <identifier id="org.bukkit.Server.reloadCommandAliases_added()"/>
  <text>
    InsertCommentsHere
  </text>
</comment>
<comment>
  <identifier id="org.bukkit.Server.reloadPermissions_added()"/>
  <text>
    InsertCommentsHere
  </text>
</comment>
<comment>
  <identifier id="org.bukkit.Server.setMaxPlayers_added(int)"/>
  <text>
    InsertCommentsHere
  </text>
</comment>
<comment>
  <identifier id="org.bukkit.Server.shutdownMessage_added()"/>
  <text>
    InsertCommentsHere
  </text>
</comment>
<comment>
  <identifier id="org.bukkit.Server.suggestPlayerNamesWhenNullTabCompletions_added()"/>
  <text>
    InsertCommentsHere
  </text>
</comment>
<comment>
  <identifier id="org.bukkit.Sound"/>
  <text>
    InsertCommentsHere
  </text>
</comment>
<comment>
  <identifier id="org.bukkit.Sound.key_added()"/>
  <text>
    InsertCommentsHere
  </text>
</comment>
<comment>
  <identifier id="org.bukkit.Tag"/>
  <text>
    InsertCommentsHere
  </text>
</comment>
<comment>
  <identifier id="org.bukkit.Tag.ARROWS"/>
  <text>
    InsertCommentsHere
  </text>
</comment>
<comment>
  <identifier id="org.bukkit.Tag.BEEHIVE_INHABITORS"/>
  <text>
    InsertCommentsHere
  </text>
</comment>
<comment>
  <identifier id="org.bukkit.Tag.IMPACT_PROJECTILES"/>
  <text>
    InsertCommentsHere
  </text>
</comment>
<comment>
  <identifier id="org.bukkit.Tag.RAIDERS"/>
  <text>
    InsertCommentsHere
  </text>
</comment>
<comment>
  <identifier id="org.bukkit.Tag.REGISTRY_ENTITIES"/>
  <text>
    InsertCommentsHere
  </text>
</comment>
<comment>
  <identifier id="org.bukkit.Tag.SKELETONS"/>
  <text>
    InsertCommentsHere
  </text>
</comment>
<comment>
  <identifier id="org.bukkit.UnsafeValues"/>
  <text>
    InsertCommentsHere
  </text>
</comment>
<comment>
  <identifier id="org.bukkit.UnsafeValues.deserializeItem_added(byte[])"/>
  <text>
    InsertCommentsHere
  </text>
</comment>
<comment>
  <identifier id="org.bukkit.UnsafeValues.getTimingsServerName_added()"/>
  <text>
    InsertCommentsHere
  </text>
</comment>
<comment>
  <identifier id="org.bukkit.UnsafeValues.getTranslationKey_added(org.bukkit.Material)"/>
  <text>
    InsertCommentsHere
  </text>
</comment>
<comment>
  <identifier id="org.bukkit.UnsafeValues.getTranslationKey_added(org.bukkit.block.Block)"/>
  <text>
    InsertCommentsHere
  </text>
</comment>
<comment>
  <identifier id="org.bukkit.UnsafeValues.getTranslationKey_added(org.bukkit.entity.EntityType)"/>
  <text>
    InsertCommentsHere
  </text>
</comment>
<comment>
  <identifier id="org.bukkit.UnsafeValues.getVersionFetcher_added()"/>
  <text>
    InsertCommentsHere
  </text>
</comment>
<comment>
  <identifier id="org.bukkit.UnsafeValues.isLegacyPlugin_added(org.bukkit.plugin.Plugin)"/>
  <text>
    InsertCommentsHere
  </text>
</comment>
<comment>
  <identifier id="org.bukkit.UnsafeValues.isSupportedApiVersion_added(java.lang.String)"/>
  <text>
    InsertCommentsHere
  </text>
</comment>
<comment>
  <identifier id="org.bukkit.UnsafeValues.legacyComponentSerializer_added()"/>
  <text>
    InsertCommentsHere
  </text>
</comment>
<comment>
  <identifier id="org.bukkit.UnsafeValues.nextEntityId_added()"/>
  <text>
    InsertCommentsHere
  </text>
</comment>
<comment>
  <identifier id="org.bukkit.UnsafeValues.reportTimings_added()"/>
  <text>
    InsertCommentsHere
  </text>
</comment>
<comment>
  <identifier id="org.bukkit.UnsafeValues.serializeItem_added(org.bukkit.inventory.ItemStack)"/>
  <text>
    InsertCommentsHere
  </text>
</comment>
<comment>
  <identifier id="org.bukkit.World"/>
  <text>
    InsertCommentsHere
  </text>
</comment>
<comment>
  <identifier id="org.bukkit.World.ChunkLoadCallback"/>
  <text>
    InsertCommentsHere
  </text>
</comment>
<comment>
  <identifier id="org.bukkit.World.audiences_added()"/>
  <text>
    InsertCommentsHere
  </text>
</comment>
<comment>
  <identifier id="org.bukkit.World.createExplosion_added(org.bukkit.entity.Entity, float)"/>
  <text>
    InsertCommentsHere
  </text>
</comment>
<comment>
  <identifier id="org.bukkit.World.createExplosion_added(org.bukkit.entity.Entity, float, boolean)"/>
  <text>
    InsertCommentsHere
  </text>
</comment>
<comment>
  <identifier id="org.bukkit.World.createExplosion_added(org.bukkit.entity.Entity, float, boolean, boolean)"/>
  <text>
    InsertCommentsHere
  </text>
</comment>
<comment>
  <identifier id="org.bukkit.World.createExplosion_added(org.bukkit.entity.Entity, org.bukkit.Location, float)"/>
  <text>
    InsertCommentsHere
  </text>
</comment>
<comment>
  <identifier id="org.bukkit.World.createExplosion_added(org.bukkit.entity.Entity, org.bukkit.Location, float, boolean)"/>
  <text>
    InsertCommentsHere
  </text>
</comment>
<comment>
  <identifier id="org.bukkit.World.createExplosion_added(org.bukkit.entity.Entity, org.bukkit.Location, float, boolean, boolean)"/>
  <text>
    InsertCommentsHere
  </text>
</comment>
<comment>
  <identifier id="org.bukkit.World.getBlockAtKey_added(long)"/>
  <text>
    InsertCommentsHere
  </text>
</comment>
<comment>
  <identifier id="org.bukkit.World.getChunkAtAsyncUrgently_added(int, int)"/>
  <text>
    InsertCommentsHere
  </text>
</comment>
<comment>
  <identifier id="org.bukkit.World.getChunkAtAsyncUrgently_added(org.bukkit.Location)"/>
  <text>
    InsertCommentsHere
  </text>
</comment>
<comment>
  <identifier id="org.bukkit.World.getChunkAtAsyncUrgently_added(org.bukkit.Location, boolean)"/>
  <text>
    InsertCommentsHere
  </text>
</comment>
<comment>
  <identifier id="org.bukkit.World.getChunkAtAsyncUrgently_added(org.bukkit.block.Block)"/>
  <text>
    InsertCommentsHere
  </text>
</comment>
<comment>
  <identifier id="org.bukkit.World.getChunkAtAsyncUrgently_added(org.bukkit.block.Block, boolean)"/>
  <text>
    InsertCommentsHere
  </text>
</comment>
<comment>
  <identifier id="org.bukkit.World.getChunkAtAsync_added(int, int)"/>
  <text>
    InsertCommentsHere
  </text>
</comment>
<comment>
  <identifier id="org.bukkit.World.getChunkAtAsync_added(int, int, boolean)"/>
  <text>
    InsertCommentsHere
  </text>
</comment>
<comment>
  <identifier id="org.bukkit.World.getChunkAtAsync_added(int, int, boolean, boolean)"/>
  <text>
    InsertCommentsHere
  </text>
</comment>
<comment>
  <identifier id="org.bukkit.World.getChunkAtAsync_added(int, int, boolean, java.util.function.Consumer&lt;org.bukkit.Chunk&gt;)"/>
  <text>
    InsertCommentsHere
  </text>
</comment>
<comment>
  <identifier id="org.bukkit.World.getChunkAtAsync_added(int, int, java.util.function.Consumer&lt;org.bukkit.Chunk&gt;)"/>
  <text>
    InsertCommentsHere
  </text>
</comment>
<comment>
  <identifier id="org.bukkit.World.getChunkAtAsync_added(int, int, org.bukkit.World.ChunkLoadCallback)"/>
  <text>
    InsertCommentsHere
  </text>
</comment>
<comment>
  <identifier id="org.bukkit.World.getChunkAtAsync_added(org.bukkit.Location)"/>
  <text>
    InsertCommentsHere
  </text>
</comment>
<comment>
  <identifier id="org.bukkit.World.getChunkAtAsync_added(org.bukkit.Location, boolean)"/>
  <text>
    InsertCommentsHere
  </text>
</comment>
<comment>
  <identifier id="org.bukkit.World.getChunkAtAsync_added(org.bukkit.Location, boolean, java.util.function.Consumer&lt;org.bukkit.Chunk&gt;)"/>
  <text>
    InsertCommentsHere
  </text>
</comment>
<comment>
  <identifier id="org.bukkit.World.getChunkAtAsync_added(org.bukkit.Location, java.util.function.Consumer&lt;org.bukkit.Chunk&gt;)"/>
  <text>
    InsertCommentsHere
  </text>
</comment>
<comment>
  <identifier id="org.bukkit.World.getChunkAtAsync_added(org.bukkit.Location, org.bukkit.World.ChunkLoadCallback)"/>
  <text>
    InsertCommentsHere
  </text>
</comment>
<comment>
  <identifier id="org.bukkit.World.getChunkAtAsync_added(org.bukkit.block.Block)"/>
  <text>
    InsertCommentsHere
  </text>
</comment>
<comment>
  <identifier id="org.bukkit.World.getChunkAtAsync_added(org.bukkit.block.Block, boolean)"/>
  <text>
    InsertCommentsHere
  </text>
</comment>
<comment>
  <identifier id="org.bukkit.World.getChunkAtAsync_added(org.bukkit.block.Block, boolean, java.util.function.Consumer&lt;org.bukkit.Chunk&gt;)"/>
  <text>
    InsertCommentsHere
  </text>
</comment>
<comment>
  <identifier id="org.bukkit.World.getChunkAtAsync_added(org.bukkit.block.Block, java.util.function.Consumer&lt;org.bukkit.Chunk&gt;)"/>
  <text>
    InsertCommentsHere
  </text>
</comment>
<comment>
  <identifier id="org.bukkit.World.getChunkAtAsync_added(org.bukkit.block.Block, org.bukkit.World.ChunkLoadCallback)"/>
  <text>
    InsertCommentsHere
  </text>
</comment>
<comment>
  <identifier id="org.bukkit.World.getChunkAt_added(long)"/>
  <text>
    InsertCommentsHere
  </text>
</comment>
<comment>
  <identifier id="org.bukkit.World.getChunkCount_added()"/>
  <text>
    InsertCommentsHere
  </text>
</comment>
<comment>
  <identifier id="org.bukkit.World.getEntityCount_added()"/>
  <text>
    InsertCommentsHere
  </text>
</comment>
<comment>
  <identifier id="org.bukkit.World.getEntity_added(java.util.UUID)"/>
  <text>
    InsertCommentsHere
  </text>
</comment>
<comment>
  <identifier id="org.bukkit.World.getHighestBlockAt_added(int, int, com.destroystokyo.paper.HeightmapType)"/>
  <text>
    InsertCommentsHere
  </text>
</comment>
<comment>
  <identifier id="org.bukkit.World.getHighestBlockAt_added(org.bukkit.Location, com.destroystokyo.paper.HeightmapType)"/>
  <text>
    InsertCommentsHere
  </text>
</comment>
<comment>
  <identifier id="org.bukkit.World.getHighestBlockYAt_added(int, int, com.destroystokyo.paper.HeightmapType)"/>
  <text>
    InsertCommentsHere
  </text>
</comment>
<comment>
  <identifier id="org.bukkit.World.getHighestBlockYAt_added(org.bukkit.Location, com.destroystokyo.paper.HeightmapType)"/>
  <text>
    InsertCommentsHere
  </text>
</comment>
<comment>
  <identifier id="org.bukkit.World.getKey_added()"/>
  <text>
    InsertCommentsHere
  </text>
</comment>
<comment>
  <identifier id="org.bukkit.World.getLocationAtKey_added(long)"/>
  <text>
    InsertCommentsHere
  </text>
</comment>
<comment>
  <identifier id="org.bukkit.World.getMoonPhase_added()"/>
  <text>
    InsertCommentsHere
  </text>
</comment>
<comment>
  <identifier id="org.bukkit.World.getNearbyEntitiesByType_added(java.lang.Class&lt;? extends T&gt;, org.bukkit.Location, double)"/>
  <text>
    InsertCommentsHere
  </text>
</comment>
<comment>
  <identifier id="org.bukkit.World.getNearbyEntitiesByType_added(java.lang.Class&lt;? extends T&gt;, org.bukkit.Location, double, double)"/>
  <text>
    InsertCommentsHere
  </text>
</comment>
<comment>
  <identifier id="org.bukkit.World.getNearbyEntitiesByType_added(java.lang.Class&lt;? extends T&gt;, org.bukkit.Location, double, double, double)"/>
  <text>
    InsertCommentsHere
  </text>
</comment>
<comment>
  <identifier id="org.bukkit.World.getNearbyEntitiesByType_added(java.lang.Class&lt;? extends T&gt;, org.bukkit.Location, double, double, java.util.function.Predicate&lt;T&gt;)"/>
  <text>
    InsertCommentsHere
  </text>
</comment>
<comment>
  <identifier id="org.bukkit.World.getNearbyEntitiesByType_added(java.lang.Class&lt;? extends T&gt;, org.bukkit.Location, double, java.util.function.Predicate&lt;T&gt;)"/>
  <text>
    InsertCommentsHere
  </text>
</comment>
<comment>
  <identifier id="org.bukkit.World.getNearbyEntitiesByType_added(java.lang.Class&lt;? extends org.bukkit.entity.Entity&gt;, org.bukkit.Location, double, double, double, java.util.function.Predicate&lt;T&gt;)"/>
  <text>
    InsertCommentsHere
  </text>
</comment>
<comment>
  <identifier id="org.bukkit.World.getNearbyLivingEntities_added(org.bukkit.Location, double)"/>
  <text>
    InsertCommentsHere
  </text>
</comment>
<comment>
  <identifier id="org.bukkit.World.getNearbyLivingEntities_added(org.bukkit.Location, double, double)"/>
  <text>
    InsertCommentsHere
  </text>
</comment>
<comment>
  <identifier id="org.bukkit.World.getNearbyLivingEntities_added(org.bukkit.Location, double, double, double)"/>
  <text>
    InsertCommentsHere
  </text>
</comment>
<comment>
  <identifier id="org.bukkit.World.getNearbyLivingEntities_added(org.bukkit.Location, double, double, double, java.util.function.Predicate&lt;org.bukkit.entity.LivingEntity&gt;)"/>
  <text>
    InsertCommentsHere
  </text>
</comment>
<comment>
  <identifier id="org.bukkit.World.getNearbyLivingEntities_added(org.bukkit.Location, double, double, java.util.function.Predicate&lt;org.bukkit.entity.LivingEntity&gt;)"/>
  <text>
    InsertCommentsHere
  </text>
</comment>
<comment>
  <identifier id="org.bukkit.World.getNearbyLivingEntities_added(org.bukkit.Location, double, java.util.function.Predicate&lt;org.bukkit.entity.LivingEntity&gt;)"/>
  <text>
    InsertCommentsHere
  </text>
</comment>
<comment>
  <identifier id="org.bukkit.World.getNearbyPlayers_added(org.bukkit.Location, double)"/>
  <text>
    InsertCommentsHere
  </text>
</comment>
<comment>
  <identifier id="org.bukkit.World.getNearbyPlayers_added(org.bukkit.Location, double, double)"/>
  <text>
    InsertCommentsHere
  </text>
</comment>
<comment>
  <identifier id="org.bukkit.World.getNearbyPlayers_added(org.bukkit.Location, double, double, double)"/>
  <text>
    InsertCommentsHere
  </text>
</comment>
<comment>
  <identifier id="org.bukkit.World.getNearbyPlayers_added(org.bukkit.Location, double, double, double, java.util.function.Predicate&lt;org.bukkit.entity.Player&gt;)"/>
  <text>
    InsertCommentsHere
  </text>
</comment>
<comment>
  <identifier id="org.bukkit.World.getNearbyPlayers_added(org.bukkit.Location, double, double, java.util.function.Predicate&lt;org.bukkit.entity.Player&gt;)"/>
  <text>
    InsertCommentsHere
  </text>
</comment>
<comment>
  <identifier id="org.bukkit.World.getNearbyPlayers_added(org.bukkit.Location, double, java.util.function.Predicate&lt;org.bukkit.entity.Player&gt;)"/>
  <text>
    InsertCommentsHere
  </text>
</comment>
<comment>
  <identifier id="org.bukkit.World.getNoTickViewDistance_added()"/>
  <text>
    InsertCommentsHere
  </text>
</comment>
<comment>
  <identifier id="org.bukkit.World.getPlayerCount_added()"/>
  <text>
    InsertCommentsHere
  </text>
</comment>
<comment>
  <identifier id="org.bukkit.World.getTickableTileEntityCount_added()"/>
  <text>
    InsertCommentsHere
  </text>
</comment>
<comment>
  <identifier id="org.bukkit.World.getTileEntityCount_added()"/>
  <text>
    InsertCommentsHere
  </text>
</comment>
<comment>
  <identifier id="org.bukkit.World.isChunkGenerated_added(long)"/>
  <text>
    InsertCommentsHere
  </text>
</comment>
<comment>
  <identifier id="org.bukkit.World.isDayTime_added()"/>
  <text>
    InsertCommentsHere
  </text>
</comment>
<comment>
  <identifier id="org.bukkit.World.setNoTickViewDistance_added(int)"/>
  <text>
    InsertCommentsHere
  </text>
</comment>
<comment>
  <identifier id="org.bukkit.World.setViewDistance_added(int)"/>
  <text>
    InsertCommentsHere
  </text>
</comment>
<comment>
  <identifier id="org.bukkit.World.spawnEntity_added(org.bukkit.Location, org.bukkit.entity.EntityType, org.bukkit.event.entity.CreatureSpawnEvent.SpawnReason)"/>
  <text>
    InsertCommentsHere
  </text>
</comment>
<comment>
  <identifier id="org.bukkit.World.spawnEntity_added(org.bukkit.Location, org.bukkit.entity.EntityType, org.bukkit.event.entity.CreatureSpawnEvent.SpawnReason, org.bukkit.util.Consumer&lt;org.bukkit.entity.Entity&gt;)"/>
  <text>
    InsertCommentsHere
  </text>
</comment>
<comment>
  <identifier id="org.bukkit.World.spawnParticle_added(org.bukkit.Particle, java.util.List&lt;org.bukkit.entity.Player&gt;, org.bukkit.entity.Player, double, double, double, int, double, double, double, double, T)"/>
  <text>
    InsertCommentsHere
  </text>
</comment>
<comment>
  <identifier id="org.bukkit.World.spawnParticle_added(org.bukkit.Particle, java.util.List&lt;org.bukkit.entity.Player&gt;, org.bukkit.entity.Player, double, double, double, int, double, double, double, double, T, boolean)"/>
  <text>
    InsertCommentsHere
  </text>
</comment>
<comment>
  <identifier id="org.bukkit.World.spawnParticle_changed(org.bukkit.Particle, double, double, double, int, double, double, double, double, T)"/>
  <text>
    InsertCommentsHere
  </text>
</comment>
<comment>
  <identifier id="org.bukkit.World.spawn_added(org.bukkit.Location, java.lang.Class&lt;T&gt;, org.bukkit.event.entity.CreatureSpawnEvent.SpawnReason)"/>
  <text>
    InsertCommentsHere
  </text>
</comment>
<comment>
  <identifier id="org.bukkit.World.spawn_added(org.bukkit.Location, java.lang.Class&lt;T&gt;, org.bukkit.event.entity.CreatureSpawnEvent.SpawnReason, org.bukkit.util.Consumer&lt;T&gt;)"/>
  <text>
    InsertCommentsHere
  </text>
</comment>
<comment>
  <identifier id="org.bukkit.World.spawn_added(org.bukkit.Location, java.lang.Class&lt;T&gt;, org.bukkit.util.Consumer&lt;T&gt;)"/>
  <text>
    InsertCommentsHere
  </text>
</comment>
<comment>
  <identifier id="org.bukkit.World.spawn_added(org.bukkit.Location, java.lang.Class&lt;T&gt;, org.bukkit.util.Consumer&lt;T&gt;, org.bukkit.event.entity.CreatureSpawnEvent.SpawnReason)"/>
  <text>
    InsertCommentsHere
  </text>
</comment>
<comment>
  <identifier id="org.bukkit.World.spawn_removed(org.bukkit.Location, java.lang.Class&lt;T&gt;, org.bukkit.util.Consumer&lt;T&gt;)"/>
  <text>
    InsertCommentsHere
  </text>
</comment>
<comment>
  <identifier id="org.bukkit.WorldBorder"/>
  <text>
    InsertCommentsHere
  </text>
</comment>
<comment>
  <identifier id="org.bukkit.WorldBorder.isInBounds_added(org.bukkit.Location)"/>
  <text>
    InsertCommentsHere
  </text>
</comment>
<comment>
  <identifier id="org.bukkit.WorldCreator"/>
  <text>
    InsertCommentsHere
  </text>
</comment>
<comment>
  <identifier id="org.bukkit.WorldCreator.ctor_added(java.lang.String, org.bukkit.NamespacedKey)"/>
  <text>
    InsertCommentsHere
  </text>
</comment>
<comment>
  <identifier id="org.bukkit.WorldCreator.ctor_added(org.bukkit.NamespacedKey)"/>
  <text>
    InsertCommentsHere
  </text>
</comment>
<comment>
  <identifier id="org.bukkit.WorldCreator.key_added()"/>
  <text>
    InsertCommentsHere
  </text>
</comment>
<comment>
  <identifier id="org.bukkit.WorldCreator.ofKey_added(org.bukkit.NamespacedKey)"/>
  <text>
    InsertCommentsHere
  </text>
</comment>
<comment>
  <identifier id="org.bukkit.WorldCreator.ofNameAndKey_added(java.lang.String, org.bukkit.NamespacedKey)"/>
  <text>
    InsertCommentsHere
  </text>
</comment>
<comment>
  <identifier id="org.spigotmc"/>
  <text>
    InsertCommentsHere
  </text>
</comment>
<comment>
  <identifier id="org.spigotmc.CustomTimingsHandler"/>
  <text>
    InsertCommentsHere
  </text>
</comment>
<comment>
  <identifier id="org.spigotmc.CustomTimingsHandler.ctor_removed(java.lang.String, org.spigotmc.CustomTimingsHandler)"/>
  <text>
    InsertCommentsHere
  </text>
</comment>
<comment>
  <identifier id="org.spigotmc.CustomTimingsHandler.printTimings_removed(java.io.PrintStream)"/>
  <text>
    InsertCommentsHere
  </text>
</comment>
<comment>
  <identifier id="org.spigotmc.CustomTimingsHandler.reload_removed()"/>
  <text>
    InsertCommentsHere
  </text>
</comment>
<comment>
  <identifier id="org.spigotmc.CustomTimingsHandler.reset_removed()"/>
  <text>
    InsertCommentsHere
  </text>
</comment>
<comment>
  <identifier id="org.spigotmc.CustomTimingsHandler.tick_removed()"/>
  <text>
    InsertCommentsHere
  </text>
</comment>

</comments>
